// class version 51.0 (51)
// access flags 0x21
public class fr/pingtimeout/tyrion/transformation/TestClassWithSynchronizedSections {

  // compiled from: TestClassWithSynchronizedSections.java

  // access flags 0x10
  final Ljava/lang/Object; lock

  // access flags 0x1
  public <init>()V
   L0
    LINENUMBER 21 L0
    ALOAD 0
    INVOKESPECIAL java/lang/Object.<init> ()V
   L1
    LINENUMBER 22 L1
    ALOAD 0
    NEW java/lang/Object
    DUP
    INVOKESPECIAL java/lang/Object.<init> ()V
    PUTFIELD fr/pingtimeout/tyrion/transformation/TestClassWithSynchronizedSections.lock : Ljava/lang/Object;
    RETURN
   L2
    LOCALVARIABLE this Lfr/pingtimeout/tyrion/transformation/TestClassWithSynchronizedSections; L0 L2 0
    MAXSTACK = 3
    MAXLOCALS = 1

  // access flags 0x8
  static staticMethodOne()J
    LDC "fr.pingtimeout.tyrion.transformation.TestClassWithSynchronizedSections"
    INVOKESTATIC fr/pingtimeout/tyrion/agent/StaticAccessor.classForName (Ljava/lang/String;)Ljava/lang/Class;
    DUP
    DUP
    INVOKESTATIC fr/pingtimeout/tyrion/agent/StaticAccessor.enteringCriticalSection (Ljava/lang/Object;)V
    MONITORENTER
   L0
    INVOKESTATIC fr/pingtimeout/tyrion/agent/StaticAccessor.enteredCriticalSection (Ljava/lang/Object;)V
   L1
    LINENUMBER 25 L1
    INVOKESTATIC fr/pingtimeout/tyrion/transformation/TestClassWithSynchronizedSections.staticMethodTwo ()J
    LDC "fr.pingtimeout.tyrion.transformation.TestClassWithSynchronizedSections"
    INVOKESTATIC fr/pingtimeout/tyrion/agent/StaticAccessor.classForName (Ljava/lang/String;)Ljava/lang/Class;
    DUP
    INVOKESTATIC fr/pingtimeout/tyrion/agent/StaticAccessor.leavingCriticalSection (Ljava/lang/Object;)V
    MONITOREXIT
    LRETURN
    TRYCATCHBLOCK L0 L2 L2 null
   L2
    LDC "fr.pingtimeout.tyrion.transformation.TestClassWithSynchronizedSections"
    INVOKESTATIC fr/pingtimeout/tyrion/agent/StaticAccessor.classForName (Ljava/lang/String;)Ljava/lang/Class;
    DUP
    INVOKESTATIC fr/pingtimeout/tyrion/agent/StaticAccessor.leavingCriticalSection (Ljava/lang/Object;)V
    MONITOREXIT
    ATHROW
    MAXSTACK = 2
    MAXLOCALS = 0

  // access flags 0x8
  static staticMethodTwo()J
    LDC "fr.pingtimeout.tyrion.transformation.TestClassWithSynchronizedSections"
    INVOKESTATIC fr/pingtimeout/tyrion/agent/StaticAccessor.classForName (Ljava/lang/String;)Ljava/lang/Class;
    DUP
    DUP
    INVOKESTATIC fr/pingtimeout/tyrion/agent/StaticAccessor.enteringCriticalSection (Ljava/lang/Object;)V
    MONITORENTER
   L0
    INVOKESTATIC fr/pingtimeout/tyrion/agent/StaticAccessor.enteredCriticalSection (Ljava/lang/Object;)V
   L1
    LINENUMBER 29 L1
    LCONST_1
    LDC "fr.pingtimeout.tyrion.transformation.TestClassWithSynchronizedSections"
    INVOKESTATIC fr/pingtimeout/tyrion/agent/StaticAccessor.classForName (Ljava/lang/String;)Ljava/lang/Class;
    DUP
    INVOKESTATIC fr/pingtimeout/tyrion/agent/StaticAccessor.leavingCriticalSection (Ljava/lang/Object;)V
    MONITOREXIT
    LRETURN
    TRYCATCHBLOCK L0 L2 L2 null
   L2
    LDC "fr.pingtimeout.tyrion.transformation.TestClassWithSynchronizedSections"
    INVOKESTATIC fr/pingtimeout/tyrion/agent/StaticAccessor.classForName (Ljava/lang/String;)Ljava/lang/Class;
    DUP
    INVOKESTATIC fr/pingtimeout/tyrion/agent/StaticAccessor.leavingCriticalSection (Ljava/lang/Object;)V
    MONITOREXIT
    ATHROW
    MAXSTACK = 2
    MAXLOCALS = 0

  // access flags 0x0
  instanceMethodOne()J
    ALOAD 0
    DUP
    DUP
    INVOKESTATIC fr/pingtimeout/tyrion/agent/StaticAccessor.enteringCriticalSection (Ljava/lang/Object;)V
    MONITORENTER
   L0
    INVOKESTATIC fr/pingtimeout/tyrion/agent/StaticAccessor.enteredCriticalSection (Ljava/lang/Object;)V
   L1
    LINENUMBER 33 L1
    ALOAD 0
    INVOKEVIRTUAL fr/pingtimeout/tyrion/transformation/TestClassWithSynchronizedSections.instanceMethodTwo ()J
    ALOAD 0
    DUP
    INVOKESTATIC fr/pingtimeout/tyrion/agent/StaticAccessor.leavingCriticalSection (Ljava/lang/Object;)V
    MONITOREXIT
    LRETURN
   L2
    LOCALVARIABLE this Lfr/pingtimeout/tyrion/transformation/TestClassWithSynchronizedSections; L1 L2 0
    TRYCATCHBLOCK L0 L3 L3 null
   L3
    ALOAD 0
    DUP
    INVOKESTATIC fr/pingtimeout/tyrion/agent/StaticAccessor.leavingCriticalSection (Ljava/lang/Object;)V
    MONITOREXIT
    ATHROW
    MAXSTACK = 2
    MAXLOCALS = 1

  // access flags 0x0
  instanceMethodTwo()J
    ALOAD 0
    DUP
    DUP
    INVOKESTATIC fr/pingtimeout/tyrion/agent/StaticAccessor.enteringCriticalSection (Ljava/lang/Object;)V
    MONITORENTER
   L0
    INVOKESTATIC fr/pingtimeout/tyrion/agent/StaticAccessor.enteredCriticalSection (Ljava/lang/Object;)V
   L1
    LINENUMBER 37 L1
    LDC 2
    ALOAD 0
    DUP
    INVOKESTATIC fr/pingtimeout/tyrion/agent/StaticAccessor.leavingCriticalSection (Ljava/lang/Object;)V
    MONITOREXIT
    LRETURN
   L2
    LOCALVARIABLE this Lfr/pingtimeout/tyrion/transformation/TestClassWithSynchronizedSections; L1 L2 0
    TRYCATCHBLOCK L0 L3 L3 null
   L3
    ALOAD 0
    DUP
    INVOKESTATIC fr/pingtimeout/tyrion/agent/StaticAccessor.leavingCriticalSection (Ljava/lang/Object;)V
    MONITOREXIT
    ATHROW
    MAXSTACK = 2
    MAXLOCALS = 1

  // access flags 0x0
  blockOne()J
    TRYCATCHBLOCK L0 L1 L2 null
    TRYCATCHBLOCK L2 L3 L2 null
   L4
    LINENUMBER 41 L4
    ALOAD 0
    GETFIELD fr/pingtimeout/tyrion/transformation/TestClassWithSynchronizedSections.lock : Ljava/lang/Object;
    DUP
    ASTORE 1
    DUP
    DUP
    INVOKESTATIC fr/pingtimeout/tyrion/agent/StaticAccessor.enteringCriticalSection (Ljava/lang/Object;)V
    MONITORENTER
   L0
    INVOKESTATIC fr/pingtimeout/tyrion/agent/StaticAccessor.enteredCriticalSection (Ljava/lang/Object;)V
   L1
    LINENUMBER 33 L1
    ALOAD 0
    INVOKEVIRTUAL fr/pingtimeout/tyrion/transformation/TestClassWithSynchronizedSections.instanceMethodTwo ()J
    ALOAD 0
    DUP
    INVOKESTATIC fr/pingtimeout/tyrion/agent/StaticAccessor.leavingCriticalSection (Ljava/lang/Object;)V
    MONITOREXIT
    LRETURN
   L2
    LOCALVARIABLE this Lfr/pingtimeout/tyrion/transformation/TestClassWithSynchronizedSections; L1 L2 0
    TRYCATCHBLOCK L0 L3 L3 null
   L3
    ALOAD 0
    DUP
    INVOKESTATIC fr/pingtimeout/tyrion/agent/StaticAccessor.leavingCriticalSection (Ljava/lang/Object;)V
    MONITOREXIT
    ATHROW
    MAXSTACK = 2
    MAXLOCALS = 1

  // access flags 0x0
  blockTwo()J
    ALOAD 0
    DUP
    DUP
    INVOKESTATIC fr/pingtimeout/tyrion/agent/StaticAccessor.enteringCriticalSection (Ljava/lang/Object;)V
    MONITORENTER
   L0
    INVOKESTATIC fr/pingtimeout/tyrion/agent/StaticAccessor.enteredCriticalSection (Ljava/lang/Object;)V
   L1
    LINENUMBER 37 L1
    LDC 2
    ALOAD 0
    DUP
    INVOKESTATIC fr/pingtimeout/tyrion/agent/StaticAccessor.leavingCriticalSection (Ljava/lang/Object;)V
    MONITOREXIT
    LRETURN
   L2
    LOCALVARIABLE this Lfr/pingtimeout/tyrion/transformation/TestClassWithSynchronizedSections; L1 L2 0
    TRYCATCHBLOCK L0 L3 L3 null
   L3
    ALOAD 0
    DUP
    INVOKESTATIC fr/pingtimeout/tyrion/agent/StaticAccessor.leavingCriticalSection (Ljava/lang/Object;)V
    MONITOREXIT
    ATHROW
    MAXSTACK = 2
    MAXLOCALS = 1

}

