// class version 51.0 (51)
// access flags 0x21
public class fr/pingtimeout/tyrion/agent/TestClassWithSynchronizedSections {

  // compiled from: TestClassWithSynchronizedSections.java

  // access flags 0x1
  public <init>()V
   L0
    LINENUMBER 21 L0
    ALOAD 0
    INVOKESPECIAL java/lang/Object.<init> ()V
    RETURN
   L1
    LOCALVARIABLE this Lfr/pingtimeout/tyrion/agent/TestClassWithSynchronizedSections; L0 L1 0
    MAXSTACK = 1
    MAXLOCALS = 1

  // access flags 0x21
  public synchronized someSynchronizedMethod()I
    ALOAD 0
    INVOKESTATIC fr/pingtimeout/tyrion/agent/LockInterceptorStaticAccessor.enteredCriticalSection (Ljava/lang/Object;)V
   L0
    LINENUMBER 23 L0
    BIPUSH 42
    ALOAD 0
    INVOKESTATIC fr/pingtimeout/tyrion/agent/LockInterceptorStaticAccessor.leavingCriticalSection (Ljava/lang/Object;)V
    IRETURN
   L1
    LOCALVARIABLE this Lfr/pingtimeout/tyrion/agent/TestClassWithSynchronizedSections; L0 L1 0
    MAXSTACK = 1
    MAXLOCALS = 1

  // access flags 0x29
  public static synchronized someStaticSynchronizedMethod()I
    LDC "fr.pingtimeout.tyrion.agent.TestClassWithSynchronizedSections"
    INVOKESTATIC fr/pingtimeout/tyrion/agent/LockInterceptorStaticAccessor.classForName (Ljava/lang/String;)Ljava/lang/Class;
    INVOKESTATIC fr/pingtimeout/tyrion/agent/LockInterceptorStaticAccessor.enteredCriticalSection (Ljava/lang/Object;)V
   L0
    LINENUMBER 27 L0
    SIPUSH 1337
    LDC "fr.pingtimeout.tyrion.agent.TestClassWithSynchronizedSections"
    INVOKESTATIC fr/pingtimeout/tyrion/agent/LockInterceptorStaticAccessor.classForName (Ljava/lang/String;)Ljava/lang/Class;
    INVOKESTATIC fr/pingtimeout/tyrion/agent/LockInterceptorStaticAccessor.leavingCriticalSection (Ljava/lang/Object;)V
    IRETURN
    MAXSTACK = 1
    MAXLOCALS = 0

  // access flags 0x1
  public methodWithSynchronizedBlock()I
    TRYCATCHBLOCK L0 L1 L2 null
    TRYCATCHBLOCK L2 L3 L2 null
   L4
    LINENUMBER 31 L4
    ALOAD 0
    DUP
    ASTORE 1
    DUP
    DUP
    INVOKESTATIC fr/pingtimeout/tyrion/agent/LockInterceptorStaticAccessor.enteringCriticalSection (Ljava/lang/Object;)V
    MONITORENTER
    INVOKESTATIC fr/pingtimeout/tyrion/agent/LockInterceptorStaticAccessor.enteredCriticalSection (Ljava/lang/Object;)V
   L0
    LINENUMBER 32 L0
    ICONST_0
    ALOAD 1
    DUP
    INVOKESTATIC fr/pingtimeout/tyrion/agent/LockInterceptorStaticAccessor.leavingCriticalSection (Ljava/lang/Object;)V
    MONITOREXIT
   L1
    IRETURN
   L2
    LINENUMBER 33 L2
   FRAME FULL [fr/pingtimeout/tyrion/agent/TestClassWithSynchronizedSections java/lang/Object] [java/lang/Throwable]
    ASTORE 2
    ALOAD 1
    DUP
    INVOKESTATIC fr/pingtimeout/tyrion/agent/LockInterceptorStaticAccessor.leavingCriticalSection (Ljava/lang/Object;)V
    MONITOREXIT
   L3
    ALOAD 2
    ATHROW
   L5
    LOCALVARIABLE this Lfr/pingtimeout/tyrion/agent/TestClassWithSynchronizedSections; L4 L5 0
    MAXSTACK = 2
    MAXLOCALS = 3
}

